dyu-0.0.5.dist-info/METADATA
dyu-0.0.5.dist-info/WHEEL
dyu-0.0.5.dist-info/entry_points.txt
dyu-0.0.5.dist-info/licenses/LICENSE
dyu/__init__.py
dyu/beancounter.py
dyu/cli.py
dyu/py.typed
dyu/settings.py
dyu-0.0.5.dist-info/RECORD
