Metadata-Version: 2.1
Name: dyu
Version: 0.0.5
Summary: A wrapper click script for setting up everything related to dyumnin semiconductors projects.
Keywords: copier-template,full-development-lifecycle,project-template,serious-scaffold
Author-Email: Vijayvithal Jahagirdar <jahagirdar.vs@gmail.com>
License: MIT
Classifier: License :: OSI Approved :: MIT License
Classifier: Operating System :: OS Independent
Classifier: Programming Language :: Python :: 3 :: Only
Classifier: Programming Language :: Python :: 3.10
Classifier: Programming Language :: Python :: 3.11
Classifier: Programming Language :: Python :: 3.12
Project-URL: Documentation, https://dyumnin.github.io/dyu
Project-URL: Issue, https://github.com/dyumnin/dyu/issues
Project-URL: Repository, https://github.com/dyumnin/dyu
Requires-Python: >=3.10
Requires-Dist: copier>=9.3.1
Requires-Dist: pydantic-settings
Requires-Dist: requests
Requires-Dist: typer[all]
Requires-Dist: xdg-base-dirs
Provides-Extra: dev
Requires-Dist: lxml>=5.3.1; extra == "dev"
